tgi_profiler/__init__.py
tgi_profiler/__main__.py
tgi_profiler/boundary_detection.py
tgi_profiler/config.py
tgi_profiler/constants.py
tgi_profiler/mllm_client.py
tgi_profiler/profiler.py
tgi_profiler/tgi_container.py
tgi_profiler/utils/__init__.py
tgi_profiler/utils/colored_logging.py
tgi_profiler/utils/prompts.py
tgi_profiler/utils/visualize_mem_profile.py
tgi_profiler-1.0.0.dist-info/LICENSE
tgi_profiler-1.0.0.dist-info/METADATA
tgi_profiler-1.0.0.dist-info/WHEEL
tgi_profiler-1.0.0.dist-info/entry_points.txt
tgi_profiler-1.0.0.dist-info/top_level.txt
tgi_profiler-1.0.0.dist-info/RECORD
