Metadata-Version: 2.2
Name: tgi-profiler
Version: 1.0.0
Summary: A framework for empirically determining maximum sequence length capabilities of LLM models deployed via TGI
Author-email: Robin Karlsson <robin@exodapt.ai>
License: GNU General Public License v3
Project-URL: Homepage, https://github.com/robin-karlsson0/tgi_profiler
Project-URL: Bug Tracker, https://github.com/robin-karlsson0/tgi-profiler/issues
Classifier: Development Status :: 3 - Alpha
Classifier: Intended Audience :: Science/Research
Classifier: License :: OSI Approved :: GNU General Public License v3 (GPLv3)
Classifier: Programming Language :: Python :: 3
Classifier: Programming Language :: Python :: 3.8
Classifier: Programming Language :: Python :: 3.9
Classifier: Programming Language :: Python :: 3.10
Classifier: Programming Language :: Python :: 3.11
Classifier: Topic :: Scientific/Engineering :: Artificial Intelligence
Requires-Python: >=3.8
License-File: LICENSE
Requires-Dist: huggingface-hub>=0.19.0
Requires-Dist: docker>=6.1.0
Requires-Dist: lark>=1.1.5
Requires-Dist: colorama>=0.4.6
Requires-Dist: anthropic>=0.5.0
Requires-Dist: openai>=1.0.0
Requires-Dist: pillow>=10.0.0
Requires-Dist: numpy>=1.24.0
Requires-Dist: transformers>=4.30.0
Requires-Dist: scipy>=1.10.0
Requires-Dist: matplotlib>=3.7.0
Requires-Dist: scikit-learn>=1.3.0
